pysimplesoap/__init__.py
pysimplesoap/client.py
pysimplesoap/server.py
pysimplesoap/simplexml.py
pysimplesoap/transport.py
PySimpleSOAP-1.8.22.dist-info/METADATA
PySimpleSOAP-1.8.22.dist-info/WHEEL
PySimpleSOAP-1.8.22.dist-info/top_level.txt
PySimpleSOAP-1.8.22.dist-info/RECORD
