Metadata-Version: 2.1
Name: PySimpleSOAP
Version: 1.8.22
Summary: Python Simple SOAP Library
Home-page: https://github.com/pysimplesoap/pysimplesoap/tree/stable
Author: Mariano Reingart
Author-email: reingart@gmail.com
